[
    {
        "name": "le premier hôpital affilié de l'université de Soochow",
        "level": "tertiaire",
        "general_or_specialized": "hôpital général",
        "public_or_private": "public",
        "area": "District de Gusu",
        "address": "numéro 188 de la rue Shizi",
        "phone": "65223637",
        "registration_time": "7:15-11:00, 11:15-16:00",
        "service_time": "7 h 45 à 11 h 30 et de 13 h 00 à 16 h 30",
        "bus_routes": "N° 2 (Tour), N° 40, N° 50, N° 202, N° 529, N° 200, N° 811, N° 89, N° 8, N° 55, N° 204, N° 309, ou N° 501",
        "metro_station": "true",
        "key_departments": [
            "cardiovasculaire",
            "néphrologie",
            "sang",
            "neurologie",
            "chirurgie générale",
            "gynécologie",
            "endocrinologie",
            "gastro-entérologie",
            "psychologie",
            "brûler",
            "oncologie",
            "neurochirurgie",
            "respiratoire",
            "urologie",
            "ophtalmologie"
        ],
        "ct": "true",
        "3.0t_mri": "true",
        "dsa": "true"
    },
    {
        "name": "le Second Hôpital Affilié de l'Université de Soochow",
        "level": "tertiaire",
        "general_or_specialized": "hôpital général",
        "public_or_private": "public",
        "area": "District de Gusu",
        "address": "n° 1055, route Sanxiang",
        "phone": "68282030",
        "registration_time": "7:00-11:30,12:00-16:30",
        "service_time": "8 h 00 à 12 h 00 et de 13 h 00 à 16 h 45",
        "bus_routes": "N° 2, N° 35, N° 38, N° 39, N° 40, N° 51, N° 60, N° 68, N° 69, N° 89, N° 303, N° 304, N° 308, N° 317, N° 321, N° 502, ou N° 931",
        "metro_station": "true",
        "key_departments": [
            "cardiovasculaire",
            "néphrologie",
            "sang",
            "neurologie",
            "chirurgie générale",
            "gynécologie",
            "endocrinologie",
            "gastro-entérologie",
            "oncologie",
            "neurochirurgie",
            "respiratoire",
            "urologie"
        ],
        "ct": "true",
        "3.0t_mri": "true",
        "dsa": "true"
    },
    {
        "name": "l'hôpital des enfants de l'université de Soochow",
        "level": "tertiaire",
        "general_or_specialized": "hôpital spécialisé",
        "public_or_private": "public",
        "area": "Parc industriel de Suzhou",
        "address": "Au 92, rue Zhongnan",
        "phone": "80693588",
        "registration_time": "7:15-16:00",
        "service_time": "7:45-11:00, 13:00-16:00",
        "bus_routes": "n° 111, n° 209, n° 219, n° 528, n° 27, n° 100, n° 116, ou n° 168",
        "metro_station": "true",
        "key_departments": [
            "néphrologie",
            "sang",
            "cardiovasculaire",
            "neurologie",
            "chirurgie générale",
            "endocrinologie",
            "gastro-entérologie",
            "neurochirurgie",
            "respiratoire",
            "pédiatrique",
            "urologie"
        ],
        "ct": "true",
        "3.0t_mri": "true",
        "dsa": "true"
    },
    {
        "name": "Hôpital municipal de Suzhou (siège)",
        "level": "tertiaire",
        "general_or_specialized": "hôpital général",
        "public_or_private": "public",
        "area": "District de Gusu",
        "address": "No. 26, rue Daoqian",
        "phone": "69009090",
        "registration_time": "7:30-11:30, 12:30-16:30",
        "service_time": "8:00-12:00, 13:00-17:00",
        "bus_routes": "n° 38, n° 40, n° 200, n° 308, n° 501, n° 511, ou n° 931",
        "metro_station": "true",
        "key_departments": [
            "neurologie",
            "endocrinologie",
            "gastro-entérologie",
            "stomatologie",
            "pédiatrique"
        ],
        "ct": "true",
        "3.0t_mri": "true",
        "dsa": "true"
    },
    {
        "name": "l'hôpital municipal de Suzhou (filiale Est)",
        "level": "tertiaire",
        "general_or_specialized": "hôpital général",
        "public_or_private": "public",
        "area": "District de Gusu",
        "address": "n° 16, route ouest Baita",
        "phone": "62364155",
        "registration_time": "7:30-11:30, 12:30-16:30",
        "service_time": "8:00-12:00, 13:00-17:00",
        "bus_routes": "No. 301 ou No. 305",
        "metro_station": "N/A",
        "key_departments": [
            "cardiovasculaire",
            "gynécologie",
            "endocrinologie",
            "oncologie",
            "gastro-entérologie",
            "urologie"
        ],
        "ct": "true",
        "3.0t_mri": "N/A",
        "dsa": "true"
    },
    {
        "name": "Hôpital municipal de Suzhou (branche nord)",
        "level": "tertiaire",
        "general_or_specialized": "hôpital général",
        "public_or_private": "public",
        "area": "District de Gusu",
        "address": "No. 242, Guangji Road",
        "phone": "69009090",
        "registration_time": "7:15-16:45",
        "service_time": "8:00-12:00, 13:00-17:00",
        "bus_routes": "n° 7, n° 34, n° 44, n° 64, n° 85, n° 304, n° 315, n° 317, n° 318, n° 406, n° 415, n° 442, n° 522, n° 816, n° 921 ou n° 949.",
        "metro_station": "true",
        "key_departments": [
            "brûler",
            "gastro-entérologie"
        ],
        "ct": "true",
        "3.0t_mri": "true",
        "dsa": "true"
    },
    {
        "name": "L'hôpital de médecine traditionnelle chinoise de Suzhou",
        "level": "tertiaire",
        "general_or_specialized": "hôpital spécialisé",
        "public_or_private": "public",
        "area": "District de Gusu",
        "address": "n° 889, Route Ouest Wuzhong",
        "phone": "65222220",
        "registration_time": "7:00-11:00,12:00-16:30",
        "service_time": "7:45-11:00, 13:00-17:00",
        "bus_routes": "n° 37, n° 47, n° 331, n° 900, ou n° 921",
        "metro_station": "true",
        "key_departments": [
            "néphrologie",
            "cardiovasculaire",
            "oncologie",
            "respiratoire",
            "urologie",
            "gynécologie"
        ],
        "ct": "true",
        "3.0t_mri": "N/A",
        "dsa": "true"
    },
    {
        "name": "hôpital Suzhou Kowloon",
        "level": "tertiaire",
        "general_or_specialized": "hôpital général",
        "public_or_private": "privé",
        "area": "Parc industriel de Suzhou",
        "address": "numéro 118 de la rue Wansheng",
        "phone": "62629999",
        "registration_time": "7:30-11:30, 12:30-16:30",
        "service_time": "8:00-12:00, 13:00-17:00",
        "bus_routes": "n° 2, n° 47, n° 106, n° 206, n° 215, n° 258, n° 6, n° 108, n° 110, n° 116, ou n° 166",
        "metro_station": "N/A",
        "key_departments": [
            "cardiovasculaire",
            "oncologie",
            "neurochirurgie",
            "stomatologie",
            "pédiatrique"
        ],
        "ct": "true",
        "3.0t_mri": "true",
        "dsa": "true"
    },
    {
        "name": "L'hôpital du village de science et technologie de Suzhou",
        "level": "tertiaire",
        "general_or_specialized": "hôpital général",
        "public_or_private": "public",
        "area": "Nouveau district de Suzhou",
        "address": "numéro 1 de la rue Lijiang",
        "phone": "33322120",
        "registration_time": "7:30-11:30, 12:30-16:30",
        "service_time": "8:00-12:00, 13:00-17:00",
        "bus_routes": "N° 852, N° 441, N° 363, N° 336, N° 330, ou N° 63",
        "metro_station": "true",
        "key_departments": [
            "urologie",
            "oncologie",
            "neurochirurgie",
            "gastro-entérologie"
        ],
        "ct": "true",
        "3.0t_mri": "true",
        "dsa": "true"
    },
    {
        "name": "l'hôpital Suzhou Guangji",
        "level": "tertiaire",
        "general_or_specialized": "hôpital spécialisé",
        "public_or_private": "public",
        "area": "District de Xiangcheng",
        "address": "n° 11 de la route Guangqian",
        "phone": "65331356",
        "registration_time": "7:00-16:50",
        "service_time": "8:00-17:00",
        "bus_routes": "N° 801 et N° 807",
        "metro_station": "N/A",
        "key_departments": [
            "psychologie"
        ],
        "ct": "true",
        "3.0t_mri": "true",
        "dsa": "N/A"
    },
    {
        "name": "l'hôpital intégré de médecine traditionnelle chinoise et occidentale de Suzhou",
        "level": "tertiaire",
        "general_or_specialized": "hôpital spécialisé",
        "public_or_private": "public",
        "area": "District de Wuzhong",
        "address": "n° 39 de la rue Xiashatang",
        "phone": "66519100",
        "registration_time": "7:45-11:45, 13:30-16:45",
        "service_time": "8:00-12:00,13:30-16:45",
        "bus_routes": "n° 2, n° 43, n° 63, n° 64, n° 65, n° 312, n° 315, n° 326, n° 505, n° 506, n° 508, n° 511, n° 512, n° 621, n° 663, n° 691, ou n° 692",
        "metro_station": "N/A",
        "key_departments": [
            "cardiovasculaire",
            "néphrologie",
            "oncologie",
            "neurochirurgie",
            "respiratoire"
        ],
        "ct": "true",
        "3.0t_mri": "N/A",
        "dsa": "N/A"
    },
    {
        "name": "Le cinquième hôpital populaire de la ville de Suzhou",
        "level": "tertiaire",
        "general_or_specialized": "hôpital spécialisé",
        "public_or_private": "public",
        "area": "District de Xiangcheng",
        "address": "numéro 10 de la rue Guangqian",
        "phone": "87806050",
        "registration_time": "7:30-11:30, 13:00-16:30",
        "service_time": "8:00-11:30,13:00-16:30",
        "bus_routes": "N° 801 et N° 807",
        "metro_station": "N/A",
        "key_departments": [
            "dermatologie"
        ],
        "ct": "true",
        "3.0t_mri": "N/A",
        "dsa": "N/A"
    },
    {
        "name": "hôpital du peuple de SND",
        "level": "secondaire",
        "general_or_specialized": "hôpital général",
        "public_or_private": "public",
        "area": "Nouveau district de Suzhou",
        "address": "95 route de Huashan",
        "phone": "66612006",
        "registration_time": "7:15-11:20, 13:00-16:45",
        "service_time": "7:45-11:30, 13:30-17:00",
        "bus_routes": "n° 44, n° 301, n° 302, n° 325, n° 332, n° 357, ou n° 442",
        "metro_station": "true",
        "key_departments": [
            "cardiovasculaire",
            "ophtalmologie",
            "gynécologie"
        ],
        "ct": "true",
        "3.0t_mri": "N/A",
        "dsa": "N/A"
    },
    {
        "name": "l'hôpital populaire de Suzhou Wuzhong",
        "level": "secondaire",
        "general_or_specialized": "hôpital général",
        "public_or_private": "public",
        "area": "District de Wuzhong",
        "address": "n° 61 de la rue Dongwu North",
        "phone": "33333600",
        "registration_time": "7:45-11:45, 12:30-16:45",
        "service_time": "8:00-12:00, 13:00-17:00",
        "bus_routes": "N° 1, N° 3, N° 5, N° 55, N° 58, N° 62, N° 309, N° 318, N° 503, N° 513, N° 522, N° 553, ou N° 932",
        "metro_station": "true",
        "key_departments": [
            "gynécologie",
            "pédiatrique",
            "gastro-entérologie",
            "dermatologie"
        ],
        "ct": "true",
        "3.0t_mri": "N/A",
        "dsa": "N/A"
    },
    {
        "name": "l'hôpital populaire de Suzhou Xiangcheng",
        "level": "secondaire",
        "general_or_specialized": "hôpital général",
        "public_or_private": "public",
        "area": "District de Xiangcheng",
        "address": "numéro 1060 de la route Huayuan",
        "phone": "69571800",
        "registration_time": "7:45-11:00,13:00-16:30",
        "service_time": "7:45-11:00,13:00-16:30",
        "bus_routes": "N° 5, N° 7, N° 809, N° 814, N° 839, ou N° 878",
        "metro_station": "true",
        "key_departments": [
            "neurochirurgie"
        ],
        "ct": "true",
        "3.0t_mri": "N/A",
        "dsa": "true"
    },
    {
        "name": "l'hôpital ophtalmologique Lixiang de l'université de Soochow",
        "level": "tertiaire",
        "general_or_specialized": "hôpital spécialisé",
        "public_or_private": "privé",
        "area": "District de Gusu",
        "address": "n° 200, route Est Ganjiang",
        "phone": "33333333",
        "registration_time": "de 7 h 30 à 17 h 30",
        "service_time": "7:45-17:45",
        "bus_routes": "N° 2, N° 9, N° 32, N° 40, N° 60, N° 89, N° 112, N° 146, N° 178, N° 200, N° 202, N° 261, N° 307, N° 900, N° 923 ou N° 980",
        "metro_station": "true",
        "key_departments": [
            "ophtalmologie"
        ],
        "ct": "N/A",
        "3.0t_mri": "N/A",
        "dsa": "N/A"
    },
    {
        "name": "l'hôpital dentaire de Suzhou",
        "level": "secondaire",
        "general_or_specialized": "hôpital spécialisé",
        "public_or_private": "privé",
        "area": "District de Gusu",
        "address": "1366, route de Suzhan",
        "phone": "69290908",
        "registration_time": "7:30-12:00,13:00-17:30",
        "service_time": "8:00-12:00,13:30-17:30",
        "bus_routes": "n° 5, n° 33, n° 88, n° 101, n° 811, n° 812, n° 872, ou n° 876",
        "metro_station": "true",
        "key_departments": [
            "stomatologie"
        ],
        "ct": "true",
        "3.0t_mri": "N/A",
        "dsa": "N/A"
    }
]
